terge/__init__.py
terge/py.typed
terge/terge.py
terge-0.1.1.dist-info/METADATA
terge-0.1.1.dist-info/WHEEL
terge-0.1.1.dist-info/licenses/LICENSE
terge-0.1.1.dist-info/RECORD
